{
    "home_directory": "/home/yangheechan/",
    "subject_name": "libxml2",
    "configure_script_working_directory": "libxml2/",
    "build_script_working_directory": "libxml2/",
    "compile_command_path": "libxml2/compile_commands.json",
    "test_case_directory": "libxml2/testcases/",
    "subject_language": "C",
    "use_distributed_machines": true,
    "single_machine": {
        "machine_name": "gaster23.swtv",
        "machine_cores": 32
    },
    "target_files": [
        "libxml2/parser.c",
        "libxml2/HTMLparser.c",
        "libxml2/relaxng.c",
        "libxml2/xmlregexp.c",
        "libxml2/xmlschemas.c"
    ],
    "real_world_buggy_versions": true
}